Metadata-Version: 2.1
Name: common-extractor
Version: 0.0.1
Summary: common table or text extractor
Home-page: https://github.datagrand.com
Author: jianzhihua
Author-email: jianzhihua@datagrand.com
License: MIT
Keywords: extractor,table,text
Platform: UNKNOWN
Classifier: Intended Audience :: Developers
Classifier: License :: OSI Approved :: MIT License
Classifier: Natural Language :: English
Classifier: Programming Language :: Python :: 2.7
Classifier: Programming Language :: Python :: 3.9
Requires-Python: >=2.7.9
